dpkg/__init__.py
dpkg/apk.py
dpkg/dataset.py
dpkg/mapk.py
dpkg-0.2.3.dist-info/METADATA
dpkg-0.2.3.dist-info/WHEEL
dpkg-0.2.3.dist-info/top_level.txt
dpkg-0.2.3.dist-info/RECORD
