Metadata-Version: 2.1
Name: dpkg
Version: 0.2.3
Summary: UNKNOWN
Author: SangMinLee
Author-email: smlee@d-if.kr
License: UNKNOWN
Platform: UNKNOWN
Classifier: Programming Language :: Python :: 3
Classifier: License :: OSI Approved :: MIT License
Classifier: Operating System :: OS Independent
Requires-Python: >3.6
Requires-Dist: pyreadstat (==1.1.9)
